CONTRIBUTING.rst
LICENSE.txt
MANIFEST.in
README.rst
requirements.txt
runtests.py
setup.py
doc/Makefile
doc/source/conf.py
doc/source/tutorials/Makefile
doc/source/tutorials/draw_circles.py
doc/source/tutorials/draw_import.py
doc/source/tutorials/draw_scatter.py
doc/source/tutorials/import_surf.py
doc/source/tutorials/img/import_integrand.pdf
doc/source/tutorials/img/import_integrand.png
doc/source/tutorials/img/import_plot.pdf
doc/source/tutorials/img/import_plot.png
doc/source/tutorials/img/rings.pdf
doc/source/tutorials/img/rings.png
doc/source/tutorials/img/scatter.pdf
doc/source/tutorials/img/scatter.png
scikit_monaco.egg-info/PKG-INFO
scikit_monaco.egg-info/SOURCES.txt
scikit_monaco.egg-info/dependency_links.txt
scikit_monaco.egg-info/not-zip-safe
scikit_monaco.egg-info/top_level.txt
skmonaco/__init__.py
skmonaco/_core.c
skmonaco/_core.pyx
skmonaco/_mc.c
skmonaco/_mc.pyx
skmonaco/_miser.c
skmonaco/_miser.pyx
skmonaco/from_pts.py
skmonaco/importance.py
skmonaco/mc_base.py
skmonaco/miser.py
skmonaco/mp.py
skmonaco/random_utils.py
skmonaco/setup.py
skmonaco/uniform.py
skmonaco/benchmarks/bench_importance.py
skmonaco/benchmarks/bench_miser.py
skmonaco/benchmarks/bench_uniform.py
skmonaco/tests/miser_data_generator.py
skmonaco/tests/miser_fixture.py
skmonaco/tests/test_from_points.py
skmonaco/tests/test_importance.py
skmonaco/tests/test_miser.py
skmonaco/tests/test_seed_generator.py
skmonaco/tests/test_uniform.py
skmonaco/tests/tests_readme.tex
skmonaco/tests/utils.py